Workbook

Sheet Instructions
A1: MS Excel Practical Exam
A2: Total Questions: 30
A3: Difficulty Level: Medium
A4: Syllabus: Formulas, Logical Functions, Lookups, INDEX-MATCH, Pivot Tables & Charts, Data Analysis
A5: Attempt all questions using appropriate Excel tools/functions.

Sheet Sales_Data
A1: Order_ID | B1: Region | C1: Salesperson | D1: Product | E1: Quantity | F1: Unit_Price | G1: Sales_Date
A2: 301 | B2: North | C2: Amit | D2: Laptop | E2: 2 | F2: 45000 | G2: 05-01-2025
A3: 302 | B3: South | C3: Riya | D3: Mobile | E3: 5 | F3: 15000 | G3: 07-01-2025
A4: 303 | B4: East | C4: Kunal | D4: Tablet | E4: 3 | F4: 18000 | G4: 10-01-2025
A5: 304 | B5: West | C5: Neha | D5: Laptop | E5: 1 | F5: 45000 | G5: 12-01-2025
A6: 305 | B6: North | C6: Amit | D6: Mobile | E6: 4 | F6: 15000 | G6: 15-01-2025
A7: 306 | B7: South | C7: Riya | D7: Laptop | E7: 2 | F7: 45000 | G7: 18-01-2025

Sheet Product_Master
A1: Product | B1: Category | C1: GST_%
A2: Laptop | B2: Electronics | C2: 18
A3: Mobile | B3: Electronics | C3: 12
A4: Tablet | B4: Electronics | C4: 12

Sheet Student_Marks
A1: Student_ID | B1: Name | C1: Maths | D1: Statistics | E1: Excel | F1: Attendance_%
A2: 1 | B2: Rahul | C2: 78 | D2: 82 | E2: 85 | F2: 92
A3: 2 | B3: Sneha | C3: 88 | D3: 91 | E3: 90 | F3: 96
A4: 3 | B4: Arjun | C4: 65 | D4: 70 | E4: 72 | F4: 85
A5: 4 | B5: Pooja | C5: 92 | D5: 89 | E5: 94 | F5: 98
A6: 5 | B6: Vikas | C6: 55 | D6: 60 | E6: 58 | F6: 80

Sheet Questions
A1: 1. Calculate Total Sales for each order (Quantity × Unit_Price). | J1: 2
A2: 2. Calculate GST Amount using VLOOKUP from Product_Master. | J2: 2
A3: 3. Find Final Amount payable (Total Sales + GST). | J3: 2
A4: 4. Find Grand Total of Final Amount. | J4: 2
A5: 5. Count total number of orders using COUNTA. | J5: 2
A6: 6. Find Region-wise total sales using SUMIF. | J6: 2
A7: 7. Use IF to classify Quantity as High (>3) or Low (<=3). | J7: 2
A8: 8. Find the maximum and minimum Final Amount. | J8: 2
A9: 9. Extract month name from Sales_Date. | J9: 2
A10: 10. Sort Sales_Data by Final Amount (Descending). | J10: 2
A11: 11. Use INDEX-MATCH to fetch Product Category. | J11: 2
A12: 12. Calculate average marks of each student. | J12: 2
... A30: 30. Protect the Student_Marks sheet. | J30: 2
J32: =SUM(J1:J30) -> 60

Sheet AnswerSheet
A1: 1. Calculate Total Sales for each order (Quantity × Unit_Price).
A2: Order_ID | B2: Total Sales
A3: 301 | B3: =Sales_Data!E2*Sales_Data!F2 -> 90000
A4: 302 | B4: =Sales_Data!E3*Sales_Data!F3 -> 75000
A5: 303 | B5: =Sales_Data!E4*Sales_Data!F4 -> 54000
A6: 304 | B6: =Sales_Data!E5*Sales_Data!F5 -> 45000
A7: 305 | B7: =Sales_Data!E6*Sales_Data!F6 -> 60000
A8: 306 | B8: =Sales_Data!E7*Sales_Data!F7 -> 90000
A11: 2. Calculate GST Amount using VLOOKUP from Product_Master.
A12: Order_ID | B12: GST Amount
A13: 301 | B13: =AnswerSheet!B3*VLOOKUP(VLOOKUP(AnswerSheet!A13,Table2[#All],4,),Table1[#All],3,0)/100 -> 16200
A14: 302 | B14: =AnswerSheet!B4*VLOOKUP(VLOOKUP(AnswerSheet!A14,Table2[#All],4,),Table1[#All],3,0)/100 -> 9000
A15: 303 | B15: =AnswerSheet!B5*VLOOKUP(VLOOKUP(AnswerSheet!A15,Table2[#All],4,),Table1[#All],3,0)/100 -> 6480
A16: 304 | B16: =AnswerSheet!B6*VLOOKUP(VLOOKUP(AnswerSheet!A16,Table2[#All],4,),Table1[#All],3,0)/100 -> 8100
A17: 305 | B17: =AnswerSheet!B7*VLOOKUP(VLOOKUP(AnswerSheet!A17,Table2[#All],4,),Table1[#All],3,0)/100 -> 7200
A18: 306 | B18: =AnswerSheet!B8*VLOOKUP(VLOOKUP(AnswerSheet!A18,Table2[#All],4,),Table1[#All],3,0)/100 -> 16200
A21: 3. Find Final Amount payable (Total Sales + GST).
A22: Order_ID | B22: Final Amount
A23: 301 | B23: =B3+B13 -> 106200
A24: 302 | B24: =B4+B14 -> 84000
A25: 303 | B25: =B5+B15 -> 60480
A26: 304 | B26: =B6+B16 -> 53100
A27: 305 | B27: =B7+B17 -> 67200
A28: 306 | B28: =B8+B18 -> 106200
A31: 4. Find Grand Total of Final Amount.
A32: Grand Total | C32: =SUM(Table6[[Final Amount ]]) -> 477180
A35: 5. Count total number of orders using COUNTA.
A36: Total number of orders | C36: =COUNTA(Table2[Salesperson]) -> 6
A39: 6. Find Region-wise total sales using SUMIF.
A40: Region | B40: Total Sales
A41: North | B41: =SUMIF(Table2[Region],"North",Table6[[Final Amount ]]) -> 173400
A42: South | B42: =SUMIF(Table2[Region],"South",Table6[[Final Amount ]]) -> 190200
A43: East | B43: =SUMIF(Table2[Region],"East",Table6[[Final Amount ]]) -> 60480
A44: West | B44: =SUMIF(Table2[Region],"West",Table6[[Final Amount ]]) -> 53100
A47: 7. Use IF to classify Quantity as High (>3) or Low (<=3).
A48: Order_ID | B48: Is Quality High or Low
A49: 301 | B49: =IF(Sales_Data!E2>3,"High","Low") -> Low
A50: 302 | B50: =IF(Sales_Data!E3>3,"High","Low") -> High
A51: 303 | B51: =IF(Sales_Data!E4>3,"High","Low") -> Low
A52: 304 | B52: =IF(Sales_Data!E5>3,"High","Low") -> Low
A53: 305 | B53: =IF(Sales_Data!E6>3,"High","Low") -> High
A54: 306 | B54: =IF(Sales_Data!E7>3,"High","Low") -> Low
A57: 8. Find the maximum and minimum Final Amount.
A58: Maximum | C58: =MAX(Table6[[Final Amount ]]) -> 106200
A59: Minimum | C59: =MIN(Table6[[Final Amount ]]) -> 53100
A62: 9. Extract month name from Sales_Date.
A63: Order_ID | B63: Sales_Date
A64: 301 | B64: 45662
A65: 302 | B65: 45663
A66: 303 | B66: 45664
A67: 304 | B67: 45665
A68: 305 | B68: 45666
A69: 306 | B69: 45667
A72: 10. Sort Sales_Data by Final Amount (Descending).
A73: Order_ID | B73: Final Amount
A74: 306 | B74: 106200
A75: 301 | B75: 106200
A76: 302 | B76: 84000
A77: 303 | B77: 67200
A78: 304 | B78: 60480
A79: 305 | B79: 53100
A82: 11. Use INDEX-MATCH to fetch Product Category.
A90: 12. Calculate average marks of each student.
A91: Student_ID | B91: Name | C91: Average Marks
A92: 1 | B92: Rahul | C92: =AVERAGE(Student_Marks!C2:E2) -> 81.666667
A93: 2 | B93: Sneha | C93: =AVERAGE(Student_Marks!C3:E3) -> 89.666667
A94: 3 | B94: Arjun | C94: =AVERAGE(Student_Marks!C4:E4) -> 69
A95: 4 | B95: Pooja | C95: =AVERAGE(Student_Marks!C5:E5) -> 91.666667
A96: 5 | B96: Vikas | C96: =AVERAGE(Student_Marks!C6:E6) -> 57.666667
A99: 13. Find the topper based on average marks.
A100: Topper | C100: =_xlfn.XLOOKUP(MAX(Table10[Average Marks]), Table10[Average Marks],Table10[Name]) -> Pooja
A103: 14. Count students with Attendance above 90%.
A104: Number of students | C104: =COUNTIF(Table3[Attendance_%],">90") -> 3
A107: 15. Use IF to classify students as Eligible (Attendance >= 85%).
A108: Student_ID | B108: Name | C108: Is Eligible?
A109: 1 | B109: Rahul | C109: =IF(Student_Marks!F2 >=85,"Eligible","Not Eligilbe") -> Eligible
A110: 2 | B110: Sneha | C110: =IF(Student_Marks!F3 >=85,"Eligible","Not Eligilbe") -> Eligible
A111: 3 | B111: Arjun | C111: =IF(Student_Marks!F4 >=85,"Eligible","Not Eligilbe") -> Eligible
A112: 4 | B112: Pooja | C112: =IF(Student_Marks!F5 >=85,"Eligible","Not Eligilbe") -> Eligible
A113: 5 | B113: Vikas | C113: =IF(Student_Marks!F6 >=85,"Eligible","Not Eligilbe") -> Not Eligilbe
A116: 16. Create a Pivot Table showing Product-wise Total Sales.
A117: Row Labels | B117: Sum of Maths | C117: Sum of Statistics | D117: Sum of Excel
A118: Arjun | B118: 65 | C118: 70 | D118: 72
A119: Pooja | B119: 92 | C119: 89 | D119: 94
A120: Rahul | B120: 78 | C120: 82 | D120: 85
A121: Sneha | B121: 88 | C121: 91 | D121: 90
A122: Vikas | B122: 55 | C122: 60 | D122: 58
A123: Grand Total | B123: 378 | C123: 392 | D123: 399
A124: 17. Create a Pivot Table showing Region-wise Total Sales.
A125: Row Labels | B125: Sum of Total Sales
A126: East | B126: 54000
A127: North | B127: 150000
A128: South | B128: 165000
A129: West | B129: 45000
A130: Grand Total | B130: 414000
A133: 18. Insert a Pivot Chart for Product-wise Sales.
A150: 19. Create a Bar Chart for Student Excel marks.
A177: 20. Find Median of Statistics marks.
A178: Student_ID | B178: Name | C178: Median
A179: 1 | B179: Rahul | C179: =MEDIAN(Student_Marks!C2:E2) -> 82
...
